Metadata-Version: 1.0
Name: nosexcover
Version: 1.0.5
Summary: Extends nose.plugins.cover to add Cobertura-style XML reports
Home-page: http://github.com/cmheisel/nose-xcover/
Author: Chris Heisel
Author-email: chris@heisel.org
License: BSD
Platform: UNKNOWN
Classifier: Development Status :: 4 - Beta
Classifier: Intended Audience :: Developers
Classifier: License :: OSI Approved :: BSD License
Classifier: Operating System :: OS Independent
Classifier: Programming Language :: Python
Classifier: Topic :: Software Development :: Libraries :: Python Modules
